{"v":"4.8.0","meta":{"g":"LottieFiles AE 1.1.0","a":"","k":"","d":"","tc":""},"fr":30,"ip":0,"op":150,"w":500,"h":500,"nm":"11 - Boxing","ddd":0,"assets":[],"layers":[{"ddd":0,"ind":2,"ty":4,"nm":"Punching bag","sr":1,"ks":{"o":{"a":0,"k":100,"ix":11},"r":{"a":1,"k":[{"i":{"x":[0.2],"y":[1]},"o":{"x":[0.8],"y":[0]},"t":0,"s":[0]},{"i":{"x":[0.2],"y":[1]},"o":{"x":[0.8],"y":[0]},"t":16,"s":[18]},{"i":{"x":[0.2],"y":[1]},"o":{"x":[0.8],"y":[0]},"t":36,"s":[40]},{"i":{"x":[0.2],"y":[1]},"o":{"x":[0.8],"y":[0]},"t":56,"s":[18]},{"i":{"x":[0.2],"y":[1]},"o":{"x":[0.8],"y":[0]},"t":76,"s":[44]},{"i":{"x":[0.2],"y":[1]},"o":{"x":[0.8],"y":[0]},"t":96,"s":[18]},{"i":{"x":[0.2],"y":[1]},"o":{"x":[0.8],"y":[0]},"t":116,"s":[43]},{"i":{"x":[0.2],"y":[1]},"o":{"x":[0.8],"y":[0]},"t":136,"s":[18]},{"t":150,"s":[0]}],"ix":10},"p":{"a":1,"k":[{"i":{"x":0.2,"y":1},"o":{"x":0.8,"y":0},"t":0,"s":[260.506,229.996,0],"to":[-14,-3.833,0],"ti":[0,0,0]},{"i":{"x":0.2,"y":1},"o":{"x":0.8,"y":0},"t":16,"s":[176.506,206.996,0],"to":[0,0,0],"ti":[0,0,0]},{"i":{"x":0.2,"y":1},"o":{"x":0.8,"y":0},"t":36,"s":[350.506,158.996,0],"to":[0,0,0],"ti":[0,0,0]},{"i":{"x":0.2,"y":1},"o":{"x":0.8,"y":0},"t":56,"s":[182.506,238.996,0],"to":[0,0,0],"ti":[0,0,0]},{"i":{"x":0.2,"y":1},"o":{"x":0.8,"y":0},"t":76,"s":[346.506,264.996,0],"to":[0,0,0],"ti":[0,0,0]},{"i":{"x":0.2,"y":1},"o":{"x":0.8,"y":0},"t":96,"s":[192.506,342.996,0],"to":[0,0,0],"ti":[0,0,0]},{"i":{"x":0.2,"y":1},"o":{"x":0.8,"y":0},"t":116,"s":[340.506,364.996,0],"to":[0,0,0],"ti":[0,0,0]},{"i":{"x":0.2,"y":1},"o":{"x":0.8,"y":0},"t":136,"s":[192.506,328.996,0],"to":[0,0,0],"ti":[-11.333,16.5,0]},{"t":150,"s":[260.506,229.996,0]}],"ix":2},"a":{"a":0,"k":[222.188,164.688,0],"ix":1},"s":{"a":1,"k":[{"i":{"x":[0.2,0.2,0.2],"y":[1,1,1]},"o":{"x":[0.8,0.8,0.8],"y":[0,0,0]},"t":0,"s":[100,100,100]},{"i":{"x":[0.2,0.2,0.2],"y":[1,1,1]},"o":{"x":[0.8,0.8,0.8],"y":[0,0,0]},"t":16,"s":[75,75,100]},{"i":{"x":[0.2,0.2,0.2],"y":[1,1,1]},"o":{"x":[0.8,0.8,0.8],"y":[0,0,0]},"t":136,"s":[75,75,100]},{"t":150,"s":[100,100,100]}],"ix":6}},"ao":0,"shapes":[{"ty":"gr","it":[{"ind":0,"ty":"sh","ix":1,"ks":{"a":0,"k":{"i":[[0.852,-4.71],[0.013,0.006],[0.019,-0.039],[0.027,-0.077],[0.173,-0.729],[0.236,-2.733],[-0.028,-1.592],[-0.211,-1.744],[-0.388,-1.836],[-0.676,-1.806],[-0.384,-0.89],[-0.414,-0.876],[-1.014,-1.577],[-1.102,-1.349],[-0.554,-0.61],[-0.544,-0.543],[-0.953,-0.825],[-0.719,-0.558],[0,0],[1.674,0.764],[1.152,0.593],[1.39,0.813],[0.731,0.476],[0.734,0.572],[1.538,1.374],[1.453,1.651],[0.665,0.899],[0.63,0.941],[1.089,1.985],[0.773,2.032],[0.545,1.939],[0.338,1.746],[0.058,2.182],[-0.023,0.646],[-0.006,0.126],[-0.01,0.109],[-0.003,0.025],[-4.71,-0.853]],"o":[[0.005,-0.024],[-0.011,0.017],[-0.02,0.059],[-0.106,0.321],[-0.359,1.446],[-0.094,1.366],[0.02,1.592],[0.175,1.756],[0.45,1.81],[0.311,0.917],[0.355,0.908],[0.861,1.732],[1.029,1.562],[0.528,0.698],[0.553,0.611],[1.084,1.088],[0.937,0.845],[1.417,1.163],[0,0],[-0.854,-0.363],[-1.167,-0.572],[-0.697,-0.406],[-0.733,-0.476],[-1.51,-1.096],[-1.522,-1.39],[-0.709,-0.836],[-0.695,-0.881],[-1.313,-1.853],[-1.027,-2.008],[-0.809,-2.022],[-0.555,-1.938],[-0.631,-3.5],[-0.036,-1.087],[0.008,-0.164],[0.014,-0.161],[0.025,-0.255],[0.853,-4.71],[4.709,0.852]],"v":[[-1.588,-21.596],[-1.632,-21.48],[-1.673,-21.425],[-1.743,-21.221],[-2.184,-19.641],[-3.184,-13.251],[-3.335,-8.794],[-3.02,-3.764],[-2.11,1.618],[-0.488,7.094],[0.574,9.798],[1.793,12.436],[4.634,17.406],[7.822,21.812],[9.457,23.767],[11.061,25.551],[14.071,28.514],[16.53,30.693],[18.757,32.52],[16.126,31.319],[13.145,29.819],[9.355,27.654],[7.252,26.28],[5.043,24.717],[0.475,20.983],[-4.02,16.424],[-6.147,13.861],[-8.153,11.137],[-11.701,5.326],[-14.475,-0.74],[-16.483,-6.714],[-17.775,-12.27],[-18.72,-20.954],[-18.718,-23.578],[-18.699,-24.014],[-18.663,-24.421],[-18.645,-24.682],[-8.572,-31.667]],"c":true},"ix":2},"nm":"Path 1","mn":"ADBE Vector Shape - Group","hd":false},{"ty":"fl","c":{"a":0,"k":[0.830999995213,0.277999997606,0.184000007779,1],"ix":4,"x":"var $bm_rt;\ntry {\n    $bm_rt = thisComp.layer('Controller').effect('Color')('ADBE Color Control-0001');\n} catch (e) {\n    $bm_rt = value;\n}"},"o":{"a":0,"k":100,"ix":5},"r":1,"bm":0,"nm":"Fill 1","mn":"ADBE Vector Graphic - Fill","hd":false},{"ty":"tr","p":{"a":0,"k":[290.004,235.879],"ix":2},"a":{"a":0,"k":[0,0],"ix":1},"s":{"a":0,"k":[100,100],"ix":3},"r":{"a":0,"k":0,"ix":6},"o":{"a":0,"k":100,"ix":7},"sk":{"a":0,"k":0,"ix":4},"sa":{"a":0,"k":0,"ix":5},"nm":"Transform"}],"nm":"Group 1","np":2,"cix":2,"bm":0,"ix":1,"mn":"ADBE Vector Group","hd":false},{"ty":"gr","it":[{"ind":0,"ty":"sh","ix":1,"ks":{"a":0,"k":{"i":[[0,0],[-23.856,-23.856],[0,0],[24.015,-24.015],[24.933,21.244],[2.008,14.496]],"o":[[23.899,-23.813],[0,0],[24.015,24.016],[-23.163,23.163],[-12.164,-10.365],[0,0]],"v":[[-74.355,-63.729],[13.001,-63.129],[50.34,-25.789],[50.34,61.54],[-35.284,66.298],[-56.542,27.525]],"c":false},"ix":2},"nm":"Path 1","mn":"ADBE Vector Shape - Group","hd":false},{"ty":"fl","c":{"a":0,"k":[0.941000007181,0.368999974868,0.337000020345,1],"ix":4,"x":"var $bm_rt;\ntry {\n    $bm_rt = thisComp.layer('Controller').effect('Color 2')('ADBE Color Control-0001');\n} catch (e) {\n    $bm_rt = value;\n}"},"o":{"a":0,"k":100,"ix":5},"r":1,"bm":0,"nm":"Fill 1","mn":"ADBE Vector Graphic - Fill","hd":false},{"ty":"tr","p":{"a":0,"k":[172.686,106.236],"ix":2},"a":{"a":0,"k":[0,0],"ix":1},"s":{"a":0,"k":[100,100],"ix":3},"r":{"a":0,"k":0,"ix":6},"o":{"a":0,"k":100,"ix":7},"sk":{"a":0,"k":0,"ix":4},"sa":{"a":0,"k":0,"ix":5},"nm":"Transform"}],"nm":"Group 2","np":2,"cix":2,"bm":0,"ix":2,"mn":"ADBE Vector Group","hd":false},{"ty":"gr","it":[{"ind":0,"ty":"sh","ix":1,"ks":{"a":0,"k":{"i":[[0,0],[-27.993,-27.993],[0,0],[28.18,-28.18],[29.256,24.928],[2.357,17.01]],"o":[[28.043,-27.942],[0,0],[28.18,28.18],[-27.179,27.179],[-14.274,-12.163],[0,0]],"v":[[-84.909,-68.511],[12.915,-74.402],[56.729,-30.588],[56.729,71.884],[-43.742,77.467],[-63.71,30.601]],"c":false},"ix":2},"nm":"Path 1","mn":"ADBE Vector Shape - Group","hd":false},{"ty":"fl","c":{"a":0,"k":[0.830999995213,0.277999997606,0.184000007779,1],"ix":4,"x":"var $bm_rt;\ntry {\n    $bm_rt = thisComp.layer('Controller')('Effects')('Color')('ADBE Color Control-0001');\n} catch (e) {\n    $bm_rt = value;\n}"},"o":{"a":0,"k":100,"ix":5},"r":1,"bm":0,"nm":"Fill 1","mn":"ADBE Vector Graphic - Fill","hd":false},{"ty":"tr","p":{"a":0,"k":[183.24,111.018],"ix":2},"a":{"a":0,"k":[0,0],"ix":1},"s":{"a":0,"k":[100,100],"ix":3},"r":{"a":0,"k":0,"ix":6},"o":{"a":0,"k":100,"ix":7},"sk":{"a":0,"k":0,"ix":4},"sa":{"a":0,"k":0,"ix":5},"nm":"Transform"}],"nm":"Group 3","np":2,"cix":2,"bm":0,"ix":3,"mn":"ADBE Vector Group","hd":false},{"ty":"gr","it":[{"ind":0,"ty":"sh","ix":1,"ks":{"a":0,"k":{"i":[[39.422,39.422],[0,0],[39.638,-36.327],[-59.535,13.745]],"o":[[0,0],[-38.371,-38.371],[-0.386,110.675],[39.422,-39.421]],"v":[[69.855,-40.136],[31.629,-78.363],[-108.891,-80.633],[69.855,103.215]],"c":true},"ix":2},"nm":"Path 1","mn":"ADBE Vector Shape - Group","hd":false},{"ty":"fl","c":{"a":0,"k":[0.941000007181,0.368999974868,0.337000020345,1],"ix":4,"x":"var $bm_rt;\ntry {\n    $bm_rt = thisComp.layer('Controller')('Effects')('Color 2')('ADBE Color Control-0001');\n} catch (e) {\n    $bm_rt = value;\n}"},"o":{"a":0,"k":100,"ix":5},"r":1,"bm":0,"nm":"Fill 1","mn":"ADBE Vector Graphic - Fill","hd":false},{"ty":"tr","p":{"a":0,"k":[286.878,117.21],"ix":2},"a":{"a":0,"k":[0,0],"ix":1},"s":{"a":0,"k":[100,100],"ix":3},"r":{"a":0,"k":0,"ix":6},"o":{"a":0,"k":100,"ix":7},"sk":{"a":0,"k":0,"ix":4},"sa":{"a":0,"k":0,"ix":5},"nm":"Transform"}],"nm":"Group 4","np":2,"cix":2,"bm":0,"ix":4,"mn":"ADBE Vector Group","hd":false},{"ty":"gr","it":[{"ind":0,"ty":"sh","ix":1,"ks":{"a":0,"k":{"i":[[39.422,39.422],[0,0],[39.638,-36.327],[-74.59,31.767]],"o":[[0,0],[-38.371,-38.371],[-0.386,110.675],[39.422,-39.422]],"v":[[64.38,-43.672],[26.153,-81.898],[-114.367,-84.168],[75.331,88.728]],"c":true},"ix":2},"nm":"Path 1","mn":"ADBE Vector Shape - Group","hd":false},{"ty":"fl","c":{"a":0,"k":[0.830999995213,0.277999997606,0.184000007779,1],"ix":4,"x":"var $bm_rt;\ntry {\n    $bm_rt = thisComp.layer('Controller')('Effects')('Color')('ADBE Color Control-0001');\n} catch (e) {\n    $bm_rt = value;\n}"},"o":{"a":0,"k":100,"ix":5},"r":1,"bm":0,"nm":"Fill 1","mn":"ADBE Vector Graphic - Fill","hd":false},{"ty":"tr","p":{"a":0,"k":[281.402,131.697],"ix":2},"a":{"a":0,"k":[0,0],"ix":1},"s":{"a":0,"k":[100,100],"ix":3},"r":{"a":0,"k":0,"ix":6},"o":{"a":0,"k":100,"ix":7},"sk":{"a":0,"k":0,"ix":4},"sa":{"a":0,"k":0,"ix":5},"nm":"Transform"}],"nm":"Group 5","np":2,"cix":2,"bm":0,"ix":5,"mn":"ADBE Vector Group","hd":false},{"ty":"gr","it":[{"ind":0,"ty":"sh","ix":1,"ks":{"a":0,"k":{"i":[[-0.387,110.675],[0,0],[-85.291,-42.641],[-24.935,24.935],[0,0]],"o":[[0,0],[-98.081,97.728],[31.541,15.768],[0,0],[-59.536,13.745]],"v":[[-0.505,-145.127],[-80.161,-139.196],[8.473,129.359],[103.044,113.92],[178.242,38.722]],"c":true},"ix":2},"nm":"Path 1","mn":"ADBE Vector Shape - Group","hd":false},{"ty":"fl","c":{"a":0,"k":[0.941000007181,0.368999974868,0.337000020345,1],"ix":4,"x":"var $bm_rt;\ntry {\n    $bm_rt = thisComp.layer('Controller')('Effects')('Color 2')('ADBE Color Control-0001');\n} catch (e) {\n    $bm_rt = value;\n}"},"o":{"a":0,"k":100,"ix":5},"r":1,"bm":0,"nm":"Fill 1","mn":"ADBE Vector Graphic - Fill","hd":false},{"ty":"tr","p":{"a":0,"k":[178.492,181.704],"ix":2},"a":{"a":0,"k":[0,0],"ix":1},"s":{"a":0,"k":[100,100],"ix":3},"r":{"a":0,"k":0,"ix":6},"o":{"a":0,"k":100,"ix":7},"sk":{"a":0,"k":0,"ix":4},"sa":{"a":0,"k":0,"ix":5},"nm":"Transform"}],"nm":"Group 6","np":2,"cix":2,"bm":0,"ix":6,"mn":"ADBE Vector Group","hd":false}],"ip":0,"op":150,"st":0,"bm":0},{"ddd":0,"ind":3,"ty":4,"nm":"Part Down","parent":2,"sr":1,"ks":{"o":{"a":0,"k":100,"ix":11},"r":{"a":0,"k":0,"ix":10},"p":{"a":0,"k":[156.52,239.648,0],"ix":2},"a":{"a":0,"k":[122.277,120.294,0],"ix":1},"s":{"a":0,"k":[100,100,100],"ix":6}},"ao":0,"shapes":[{"ty":"gr","it":[{"ind":0,"ty":"sh","ix":1,"ks":{"a":0,"k":{"i":[[0,0],[0,0],[-4.554,-12.671],[-50.737,-15.853],[-7.551,7.551],[0,0]],"o":[[0,0],[-9.52,9.521],[17.142,47.698],[10.193,3.186],[0,0],[0,0]],"v":[[-8.641,-120.984],[-107.736,-21.889],[-116.188,14.49],[-10.423,117.799],[18.459,110.68],[120.742,8.398]],"c":true},"ix":2},"nm":"Path 1","mn":"ADBE Vector Shape - Group","hd":false},{"ty":"fl","c":{"a":0,"k":[0.830999995213,0.277999997606,0.184000007779,1],"ix":4,"x":"var $bm_rt;\ntry {\n    $bm_rt = thisComp.layer('Controller')('Effects')('Color')('ADBE Color Control-0001');\n} catch (e) {\n    $bm_rt = value;\n}"},"o":{"a":0,"k":100,"ix":5},"r":1,"bm":0,"nm":"Fill 1","mn":"ADBE Vector Graphic - Fill","hd":false},{"ty":"tr","p":{"a":0,"k":[120.991,121.234],"ix":2},"a":{"a":0,"k":[0,0],"ix":1},"s":{"a":0,"k":[100,100],"ix":3},"r":{"a":0,"k":0,"ix":6},"o":{"a":0,"k":100,"ix":7},"sk":{"a":0,"k":0,"ix":4},"sa":{"a":0,"k":0,"ix":5},"nm":"Transform"}],"nm":"Group 1","np":2,"cix":2,"bm":0,"ix":1,"mn":"ADBE Vector Group","hd":false}],"ip":0,"op":150,"st":0,"bm":0}],"markers":[]}